mynodepack/__init__.py
mynodepack/formula/__init__.py
mynodepack/formula/circle_area/__init__.py
mynodepack/formula/circle_area/__main__.py
mynodepack/formula/hypotenuse/__init__.py
mynodepack/formula/hypotenuse/__main__.py
mynodepack/geometric_drawings/__init__.py
mynodepack/geometric_drawings/get_circle/__init__.py
mynodepack/geometric_drawings/get_circle/__main__.py
mynodepack/geometric_drawings/get_combined_surfs/__init__.py
mynodepack/geometric_drawings/get_combined_surfs/__main__.py
mynodepack/geometric_drawings/get_rectangle/__init__.py
mynodepack/geometric_drawings/get_rectangle/__main__.py
mynodepack/geometric_drawings/save_surface/__init__.py
mynodepack/geometric_drawings/save_surface/__main__.py
mynodepack/geometric_drawings/view_surface/__init__.py
mynodepack/geometric_drawings/view_surface/__main__.py
mynodepack/geometric_drawings/view_surface/utils.py
mynodepack-1.0.2.dist-info/METADATA
mynodepack-1.0.2.dist-info/WHEEL
mynodepack-1.0.2.dist-info/top_level.txt
mynodepack-1.0.2.dist-info/RECORD
