Metadata-Version: 2.1
Name: mynodepack
Version: 1.0.2
Summary: A template/example node pack with some dummy nodes
Home-page: https://github.com/KennedyRichard/mynodepack
Author: Kennedy Richard
Author-email: kennedy@kennedyrichard.com
License: Unlicense
Project-URL: Source, https://github.com/KennedyRichard/mynodepack
Project-URL: Bug Tracker, https://github.com/KennedyRichard/mynodepack/issues
Keywords: nodes,node,pack,example,template,nodezator
Classifier: License :: OSI Approved :: The Unlicense (Unlicense)
Classifier: Programming Language :: Python :: Implementation :: CPython
Requires-Python: >=3.7
Requires-Dist: pygame-ce
